autoesp/__init__.py
autoesp/autoesp.py
autoesp/firmwares/ESP32_GENERIC-20240105-v1.22.1.bin
autoesp/firmwares/ESP32_GENERIC-SPIRAM-20240105-v1.22.1.bin
autoesp/firmwares/ESP8266_GENERIC-20240105-v1.22.1.bin
autoesp/firmwares/ESP8266_GENERIC-FLASH_1M-20240105-v1.22.1.bin
autoesp/firmwares/LOLIN_S2_MINI-20240105-v1.22.1.uf2
autoesp-1.1.2.dist-info/LICENSE
autoesp-1.1.2.dist-info/METADATA
autoesp-1.1.2.dist-info/WHEEL
autoesp-1.1.2.dist-info/entry_points.txt
autoesp-1.1.2.dist-info/top_level.txt
autoesp-1.1.2.dist-info/RECORD
