Metadata-Version: 2.1
Name: autoesp
Version: 1.1.2
Summary: An useful CLT for auto-test espressif boards. 
Home-page: https://github.com/Dual-Points/autoesp
Author: Sen LEI
Author-email: sen.lei@outlook.com
License: BSD 3-clause
Keywords: espressif,esp,esp32,esp8266,iot,serial,clt,boards,mcu,mpu,test
Classifier: Development Status :: 3 - Alpha
Classifier: Programming Language :: Python :: 3.8
Classifier: License :: OSI Approved :: BSD License
Classifier: Operating System :: OS Independent
License-File: LICENSE
Requires-Dist: esptool
Requires-Dist: adafruit-ampy
